{"filters":[{"field":"color","values":["black","blue","brown","gray","green","navy","pink","purple","red","white","yellow","orange","multi color","olive","cream","gold"]},{"field":"pattern","values":["plain-solid","checks-plaid","stripes","textured","prints"]},{"field":"fabric","values":["cotton","linen","poly-viscose-rayon","tere-rayon"]},{"field":"shade","values":["plain-solid","checks-plaid","stripes","textured","prints"]},{"field":"style","values":["clean-look","highly-distressed","low-distressed","mildly-distressed","slash-knee"]},{"field":"fade","values":["heavy-fade","light-fade","no-fade"]}]}